glasbey/__init__.py
glasbey/_converters.py
glasbey/_glasbey.py
glasbey/_grids.py
glasbey/_internals.py
glasbey/_optimizers.py
glasbey-0.3.0.dist-info/LICENSE
glasbey-0.3.0.dist-info/METADATA
glasbey-0.3.0.dist-info/WHEEL
glasbey-0.3.0.dist-info/top_level.txt
glasbey-0.3.0.dist-info/RECORD
