Metadata-Version: 2.1
Name: glasbey
Version: 0.3.0
Summary: Algorithmically generate categorical color palettes
Home-page: https://github.com/lmcinnes
Author: Leland McInnes
Author-email: leland.mcinnes@gmail.com
Maintainer: Leland McInnes
Maintainer-email: leland.mcinnes@gmail.com
License: MIT License
Keywords: color,palette,categorical
Classifier: License :: OSI Approved :: MIT License
Classifier: Programming Language :: Python :: 3.9
Classifier: Programming Language :: Python :: 3.10
Classifier: Programming Language :: Python :: 3.11
Classifier: Programming Language :: Python :: 3.12
Classifier: Development Status :: 4 - Beta
Classifier: Operating System :: OS Independent
Requires-Python: >=3.9
License-File: LICENSE
Requires-Dist: numpy>=1.21
Requires-Dist: numba>=0.56
Requires-Dist: colorspacious>=1.1
Requires-Dist: matplotlib>=3.5
Requires-Dist: scikit-learn>=1.1
